sqlalchemy_pydantic_orm/__init__.py
sqlalchemy_pydantic_orm/main.py
tests/__init__.py
tests/main.py
tests/test_orm_specific_methods.py
tests/test_to_orm_method.py
sqlalchemy_pydantic_orm-0.1.0.dist-info/LICENSE
sqlalchemy_pydantic_orm-0.1.0.dist-info/METADATA
sqlalchemy_pydantic_orm-0.1.0.dist-info/WHEEL
sqlalchemy_pydantic_orm-0.1.0.dist-info/top_level.txt
sqlalchemy_pydantic_orm-0.1.0.dist-info/RECORD
