Metadata-Version: 2.1
Name: sqlalchemy-pydantic-orm
Version: 0.1.0
Summary: CRUD operations on nested SQLAlchemy ORM-models using Pydantic
Home-page: https://github.com/Wouterkoorn/sqlalchemy-pydantic-orm
Author: wkoorn (Wouter Koorn)
Author-email: <wouter.koorn@student.hu.nl>
License: UNKNOWN
Project-URL: Source, https://github.com/Wouterkoorn/sqlalchemy-pydantic-orm
Project-URL: Documentation, https://wouterkoorn.github.io/sqlalchemy-pydantic-orm/index.html
Project-URL: Tracker, https://github.com/Wouterkoorn/sqlalchemy-pydantic-orm/issues
Keywords: python,pydantic,sqlalchemy,ORM,nested,nesting,CRUD
Platform: UNKNOWN
Classifier: Development Status :: 3 - Alpha
Classifier: Intended Audience :: Developers
Classifier: Programming Language :: Python :: 3
Classifier: Operating System :: OS Independent
Classifier: License :: OSI Approved :: MIT License
Classifier: Natural Language :: English
Classifier: Topic :: Software Development :: Libraries :: Python Modules
Classifier: Topic :: Database
Classifier: Topic :: Database :: Database Engines/Servers
Classifier: Topic :: Software Development :: Version Control :: Git
Classifier: Topic :: Software Development :: Testing :: Unit
Classifier: Typing :: Typed
Requires-Python: >=3.8
Requires-Dist: pydantic (~=1.8.1)
Requires-Dist: sqlalchemy (~=1.4.11)
Provides-Extra: dev
Requires-Dist: pytest (>=6.2.3) ; extra == 'dev'
Requires-Dist: coverage (>=5.5) ; extra == 'dev'
Requires-Dist: flake8 (>=3.9.1) ; extra == 'dev'
Requires-Dist: black (>=20.8) ; extra == 'dev'
Requires-Dist: mypy (>=0.812) ; extra == 'dev'
Requires-Dist: pdoc3 (>=0.9.2) ; extra == 'dev'
